README.md
setup.py
chao_fib_py/__init__.py
chao_fib_py.egg-info/PKG-INFO
chao_fib_py.egg-info/SOURCES.txt
chao_fib_py.egg-info/dependency_links.txt
chao_fib_py.egg-info/entry_points.txt
chao_fib_py.egg-info/requires.txt
chao_fib_py.egg-info/top_level.txt
chao_fib_py/cmd/__init__.py
chao_fib_py/cmd/fib_numb.py
chao_fib_py/fib_calcs/__init__.py
chao_fib_py/fib_calcs/fib_number.py
chao_fib_py/fib_calcs/fib_numbers.py
tests/chao_fib_py/__init__.py
tests/chao_fib_py/fib_calcs/__init__.py
tests/chao_fib_py/fib_calcs/test_fib_number.py
tests/chao_fib_py/fib_calcs/test_fib_numbers.py